[
    {
        "material": {
            "ambient": [0.1, 0.1, 0.1],
            "diffuse": [0.88, 0.84, 0.94],
            "specular": [0.3, 0.3, 0.3],
            "n": 10,
            "alpha": 1.0,
            "texture": "flower.png"
        },
        "vertices": [
            [0.5, 1.2, 0.5],
            [0.25, 0.95, 0.5],
            [0.5, 0.7, 0.5],
            [0.75, 0.95, 0.5]
        ],
        "normals": [
            [0, 0, -1], [0, 0, -1], [0, 0, -1], [0, 0, -1]
        ],
        "uvs": [
            [0.5, 1], [0, 0.5], [0.5, 0], [1, 0.5]
        ],
        "triangles": [
            [0, 1, 2], [2, 3, 0]
        ]
    },
    {
        "material": {
            "ambient": [0.1, 0.1, 0.1],
            "diffuse": [0.71, 0.85, 0.93],
            "specular": [0.3, 0.3, 0.3],
            "n": 10,
            "alpha": 1.0,
            "texture": "mountain.png"
        },
        "vertices": [
            [-0.1, 0.1, 0.65],
            [0.5, 0.7, 0.65],
            [1.1, 0.1, 0.65]
        ],
        "normals": [
            [0, 0, -1], [0, 0, -1], [0, 0, -1]
        ],
        "uvs": [
            [0, 0], [0.5, 1], [1, 0]
        ],
        "triangles": [
            [0, 1, 2]
        ]
    },
    {
        "material": {
            "ambient": [0.1, 0.1, 0.1],
            "diffuse": [0.71, 0.85, 0.93],
            "specular": [0.3, 0.3, 0.3],
            "n": 10,
            "alpha": 1.0,
            "texture": "mountain.png"
        },
        "vertices": [
            [0.6, 0.1, 0.7],
            [1.2, 0.7, 0.7],
            [1.8, 0.1, 0.7]
        ],
        "normals": [
            [0, 0, -1], [0, 0, -1], [0, 0, -1]
        ],
        "uvs": [
            [0, 0], [0.5, 1], [1, 0]
        ],
        "triangles": [
            [0, 1, 2]
        ]
    },
    {
        "material": {
            "ambient": [0.1, 0.1, 0.1],
            "diffuse": [0.71, 0.85, 0.93],
            "specular": [0.3, 0.3, 0.3],
            "n": 10,
            "alpha": 1.0,
            "texture": "mountain.png"
        },
        "vertices": [
            [0.5, 0.1, 0.65],
            [-0.1, 0.7, 0.65],
            [-0.7, 0.1, 0.65]
        ],
        "normals": [
            [0, 0, -1], [0, 0, -1], [0, 0, -1]
        ],
        "uvs": [
            [0, 0], [0.5, 1], [1, 0]
        ],
        "triangles": [
            [0, 1, 2]
        ]
    }
]
